really/__init__.py
really/cli.py
really/workflow.tar.gz
really/tests/__init__.py
really/tests/test_cli.py
reallyrun-0.1.dist-info/LICENSE
reallyrun-0.1.dist-info/METADATA
reallyrun-0.1.dist-info/WHEEL
reallyrun-0.1.dist-info/entry_points.txt
reallyrun-0.1.dist-info/top_level.txt
reallyrun-0.1.dist-info/RECORD
