Metadata-Version: 2.1
Name: reallyrun
Version: 0.1
Summary: Not your grandmas NGS analysis - software for analyzing FASTQs from REALLY libraries
Home-page: https://github.com/claretbio/reallyrun
Author: Tobin Groth
Author-email: tobin.groth@claretbio.com
Classifier: Programming Language :: Python :: 3
Classifier: License :: OSI Approved :: MIT License
Classifier: Operating System :: OS Independent
License-File: LICENSE
Requires-Dist: pysam
Requires-Dist: snakemake
Requires-Dist: umi-tools
Requires-Dist: pyyaml
Requires-Dist: srslyumi
Requires-Dist: Cython
